vizh-0.1.3.data/purelib/vizh/__init__.py
vizh-0.1.3.data/purelib/vizh/compiler.py
vizh-0.1.3.data/purelib/vizh/crtv.obj
vizh-0.1.3.data/purelib/vizh/driver.py
vizh-0.1.3.data/purelib/vizh/ir.py
vizh-0.1.3.data/purelib/vizh/libv.h
vizh-0.1.3.data/purelib/vizh/libv.lib
vizh-0.1.3.data/purelib/vizh/libv.py
vizh-0.1.3.data/purelib/vizh/libv_decls.py
vizh-0.1.3.data/purelib/vizh/libv_vizh.h
vizh-0.1.3.data/purelib/vizh/linker.py
vizh-0.1.3.data/purelib/vizh/ocr.py
vizh-0.1.3.data/purelib/vizh/parser.py
vizh-0.1.3.data/purelib/vizh/util.py
vizh-0.1.3.dist-info/LICENSE
vizh-0.1.3.dist-info/METADATA
vizh-0.1.3.dist-info/WHEEL
vizh-0.1.3.dist-info/entry_points.txt
vizh-0.1.3.dist-info/top_level.txt
vizh-0.1.3.dist-info/RECORD
