Metadata-Version: 2.1
Name: vizh
Version: 0.1.3
Summary: A visual esoteric language
Home-page: https://github.com/tartanllama/vizh
Author: Sy Brand
Author-email: tartanllama@gmail.com
License: UNKNOWN
Project-URL: Bug Tracker, https://github.com/tartanllama/vizh/issues
Platform: UNKNOWN
Classifier: Programming Language :: Python :: 3
Classifier: License :: OSI Approved :: Apache Software License
Classifier: Operating System :: OS Independent
Requires-Python: >=3.6
License-File: LICENSE
